CHANGES.txt
MANIFEST.in
README.md
requirements.txt
setup.py
django_layers.egg-info/PKG-INFO
django_layers.egg-info/SOURCES.txt
django_layers.egg-info/dependency_links.txt
django_layers.egg-info/namespace_packages.txt
django_layers.egg-info/not-zip-safe
django_layers.egg-info/requires.txt
django_layers.egg-info/top_level.txt
layers/__init__.py
layers/finders.py
layers/handlers.py
layers/loader.py
layers/middleware.py
layers/management/__init__.py
layers/management/commands/__init__.py
layers/management/commands/collectlayers.py
layers/management/commands/runserver.py
layers/tests/__init__.py
layers/tests/conftest.py
layers/tests/test_finder.py
layers/tests/test_loader.py
layers/tests/test_middleware.py
layers/tests/pkg1/__init__.py
layers/tests/pkg1/layers/test/static/file.x
layers/tests/pkg1/layers/test/templates/test.html
layers/tests/pkg1/layers/test2/static/file.x
layers/tests/pkg1/templates/test/oldstyle.html
layers/tests/pkg2/__init__.py
layers/tests/pkg2/layers/test/templates/test.html
layers/tests/pkg2/layers/test/templates/test2.html