Metadata-Version: 1.1
Name: django-layers
Version: 0.8
Summary: Support different frontend templates/statics on same instance
Home-page: http://github.com/iivvoo/django_layers
Author: Ivo van der Wijk
Author-email: djangoprojects@in.m3r.nl
License: BSD
Platform: UNKNOWN
Classifier: Programming Language :: Python
